guimpl/__init__.py
guimpl/app.py
guimpl/controller.py
guimpl/dico_params.py
guimpl/model.py
guimpl/view.py
guimpl/custom_widgets/__init__.py
guimpl/custom_widgets/color_chooser.py
guimpl/custom_widgets/double_spinbox.py
guimpl/row_pygubu/__init__.py
guimpl/row_pygubu/autowidgets_base_frame.py
guimpl/row_pygubu/axeschoosewidgetsframe.py
guimpl/row_pygubu/axewidgetsbaseframe.py
guimpl/row_pygubu/row_pygubu_main.py
guimpl/surcouches_pygubu/__init__.py
guimpl/surcouches_pygubu/autowidgetsframe.py
guimpl/surcouches_pygubu/mainaxewidgetsframewidget.py
guimpl-0.0.2.dist-info/METADATA
guimpl-0.0.2.dist-info/WHEEL
guimpl-0.0.2.dist-info/top_level.txt
guimpl-0.0.2.dist-info/RECORD
