Metadata-Version: 2.1
Name: guimpl
Version: 0.0.2
Summary: Application pour modifier l'esthétique d'un graphique matplotlib
Author: Groupe Figure MPCI
Keywords: matplotlib,graphique,interface graphique,python,figures
Classifier: Programming Language :: Python :: 3
Classifier: Operating System :: Unix
Classifier: Operating System :: MacOS :: MacOS X
Classifier: Operating System :: Microsoft :: Windows
Requires-Dist: matplotlib
